[
{
 "fields": {
  "user": 1,
  "name": null
 },
 "model": "djangobmf.dashboard",
 "pk": 1
},
{
 "fields": {
  "user": 1,
  "name": "Project-Management"
 },
 "model": "djangobmf.dashboard",
 "pk": 2
},
{
 "fields": {
  "kwargs": "{}",
  "name": "All Projects",
  "dashboard": 2,
  "category": "",
  "url": "djangobmf:module_djangobmf_project_project:index",
  "search": ""
 },
 "model": "djangobmf.view",
 "pk": 1
},
{
 "fields": {
  "kwargs": "{}",
  "name": "Open Goals",
  "dashboard": 2,
  "category": "",
  "url": "djangobmf:module_djangobmf_task_goal:index",
  "search": "project=&referee=&completed=3"
 },
 "model": "djangobmf.view",
 "pk": 2
},
{
 "fields": {
  "kwargs": "{}",
  "name": "My Tasks",
  "dashboard": 2,
  "category": "",
  "url": "djangobmf:module_djangobmf_task_task:index",
  "search": "project=&employee=1&state=new&state=open&state=hold&state=todo&state=started&state=review&due_date=1"
 },
 "model": "djangobmf.view",
 "pk": 3
},
{
 "fields": {
  "kwargs": "{}",
  "name": "All Tasks",
  "dashboard": 2,
  "category": "",
  "url": "djangobmf:module_djangobmf_task_task:index",
  "search": "project=&employee=&state=new&state=open&state=hold&state=todo&state=started&state=review&due_date=1"
 },
 "model": "djangobmf.view",
 "pk": 4
}
]
